nixscribe/__init__.py
nixscribe/cli.py
nixscribe/editor.py
nixscribe/main.py
nixscribe-0.1.2.dist-info/licenses/LICENSE
nixscribe-0.1.2.dist-info/METADATA
nixscribe-0.1.2.dist-info/WHEEL
nixscribe-0.1.2.dist-info/entry_points.txt
nixscribe-0.1.2.dist-info/top_level.txt
nixscribe-0.1.2.dist-info/RECORD
