Metadata-Version: 2.4
Name: nixscribe
Version: 0.1.2
Summary: A CLI Text Editor that supports Syntax Highlighting for .py, .html, .css and .js files.
Author: mhasanali2010
License-Expression: MIT
Classifier: Programming Language :: Python :: 3
Classifier: Operating System :: OS Independent
Requires-Python: >=3.10
License-File: LICENSE
Requires-Dist: rich>=13.5.2
Requires-Dist: prompt_toolkit>=3.0.52
Requires-Dist: pygments>=2.17.1
Dynamic: license-file
